metric/__init__.py
metric/metric.py
metric/ztest.py
metric/model/__init__.py
metric/model/pycm/__init__.py
metric/model/pycm/__main__.py
metric/model/pycm/pycm_ci.py
metric/model/pycm/pycm_class_func.py
metric/model/pycm/pycm_compare.py
metric/model/pycm/pycm_interpret.py
metric/model/pycm/pycm_obj.py
metric/model/pycm/pycm_output.py
metric/model/pycm/pycm_overall_func.py
metric/model/pycm/pycm_param.py
metric/model/pycm/pycm_profile.py
metric/model/pycm/pycm_test.py
metric/model/pycm/pycm_util.py
metric/new/__init__.py
metric-0.10.0.dist-info/METADATA
metric-0.10.0.dist-info/RECORD
metric-0.10.0.dist-info/WHEEL
metric-0.10.0.dist-info/top_level.txt
